pydantic/__init__.py
pydantic/_migration.py
pydantic/alias_generators.py
pydantic/aliases.py
pydantic/annotated_handlers.py
pydantic/class_validators.py
pydantic/color.py
pydantic/config.py
pydantic/dataclasses.py
pydantic/datetime_parse.py
pydantic/decorator.py
pydantic/env_settings.py
pydantic/error_wrappers.py
pydantic/errors.py
pydantic/fields.py
pydantic/functional_serializers.py
pydantic/functional_validators.py
pydantic/generics.py
pydantic/json.py
pydantic/json_schema.py
pydantic/main.py
pydantic/mypy.py
pydantic/networks.py
pydantic/parse.py
pydantic/py.typed
pydantic/root_model.py
pydantic/schema.py
pydantic/tools.py
pydantic/type_adapter.py
pydantic/types.py
pydantic/typing.py
pydantic/utils.py
pydantic/validate_call_decorator.py
pydantic/validators.py
pydantic/version.py
pydantic/warnings.py
pydantic/_internal/__init__.py
pydantic/_internal/_config.py
pydantic/_internal/_core_metadata.py
pydantic/_internal/_core_utils.py
pydantic/_internal/_dataclasses.py
pydantic/_internal/_decorators.py
pydantic/_internal/_decorators_v1.py
pydantic/_internal/_discriminated_union.py
pydantic/_internal/_docs_extraction.py
pydantic/_internal/_fields.py
pydantic/_internal/_forward_ref.py
pydantic/_internal/_generate_schema.py
pydantic/_internal/_generics.py
pydantic/_internal/_git.py
pydantic/_internal/_import_utils.py
pydantic/_internal/_internal_dataclass.py
pydantic/_internal/_known_annotated_metadata.py
pydantic/_internal/_mock_val_ser.py
pydantic/_internal/_model_construction.py
pydantic/_internal/_namespace_utils.py
pydantic/_internal/_repr.py
pydantic/_internal/_schema_gather.py
pydantic/_internal/_schema_generation_shared.py
pydantic/_internal/_serializers.py
pydantic/_internal/_signature.py
pydantic/_internal/_typing_extra.py
pydantic/_internal/_utils.py
pydantic/_internal/_validate_call.py
pydantic/_internal/_validators.py
pydantic/deprecated/__init__.py
pydantic/deprecated/class_validators.py
pydantic/deprecated/config.py
pydantic/deprecated/copy_internals.py
pydantic_patched-2.11.9.dist-info/METADATA
pydantic_patched-2.11.9.dist-info/WHEEL
pydantic_patched-2.11.9.dist-info/licenses/LICENSE
pydantic_patched-2.11.9.dist-info/RECORD
